mygoogleAuth_fastAPI/__init__.py
mygoogleAuth_fastAPI/auth_router.py
mygoogleAuth_fastAPI/mygoogleAuth_fastAPI_core.py
mygoogleAuth_fastAPI-1.2.0.dist-info/METADATA
mygoogleAuth_fastAPI-1.2.0.dist-info/WHEEL
mygoogleAuth_fastAPI-1.2.0.dist-info/top_level.txt
mygoogleAuth_fastAPI-1.2.0.dist-info/RECORD
